uri/__init__.py
uri/django_uri.py
uri/middleware.py
django_uri-1.0.5.dist-info/METADATA
django_uri-1.0.5.dist-info/WHEEL
django_uri-1.0.5.dist-info/top_level.txt
django_uri-1.0.5.dist-info/RECORD
