Metadata-Version: 2.1
Name: django-uri
Version: 1.0.5
Summary: Django URI
Home-page: https://github.com/django-xxx/django-uri
Author: Hackathon
Author-email: kimi.huang@brightcells.com
License: UNKNOWN
Keywords: django-uri
Platform: UNKNOWN
Classifier: Development Status :: 5 - Production/Stable
Classifier: Environment :: Web Environment
Classifier: Framework :: Django
Classifier: Intended Audience :: Developers
Classifier: Programming Language :: Python
Classifier: Topic :: Software Development :: Libraries :: Python Modules
Classifier: Topic :: Office/Business :: Financial :: Spreadsheet
Requires-Dist: django-six
Requires-Dist: six
